setup.cfg
setup.py
fig_an225.egg-info/PKG-INFO
fig_an225.egg-info/SOURCES.txt
fig_an225.egg-info/dependency_links.txt
fig_an225.egg-info/not-zip-safe
fig_an225.egg-info/top_level.txt
fig_an225/circle/__init__.py
fig_an225/circle/code.py
fig_an225/square/__init__.py
fig_an225/square/code.py
fig_an225/triangle/__init__.py
fig_an225/triangle/code.py