Metadata-Version: 2.1
Name: fig-an225
Version: 0.0
Summary: circle, tiangle, square
Author-email: alexeykozhakin@gmail.com
